{
  "timestamp": "2025-11-27T02:15:49.288171",
  "authorization": "ALPHA-2B-COMPREHENSIVE",
  "total_tested": 10,
  "total_kept": 10,
  "elapsed_minutes": 2.8398900508880613,
  "results": [
    {
      "batch_name": "Tier 1 - First 10",
      "tested": 10,
      "kept": 10,
      "results": [
        {
          "triangle": "EUR-USD-GBP",
          "baseline_r2": 0.7079,
          "new_r2": 0.9626928101793792,
          "improvement": 0.25479281017937927,
          "improvement_pct": 35.99276877798832,
          "kept": true,
          "num_features": 10
        },
        {
          "triangle": "EUR-USD-JPY",
          "baseline_r2": 0.7079,
          "new_r2": 0.9652914293307241,
          "improvement": 0.2573914293307241,
          "improvement_pct": 36.35985722993701,
          "kept": true,
          "num_features": 10
        },
        {
          "triangle": "EUR-USD-CHF",
          "baseline_r2": 0.7079,
          "new_r2": 0.9653232625203118,
          "improvement": 0.2574232625203118,
          "improvement_pct": 36.364354078303684,
          "kept": true,
          "num_features": 10
        },
        {
          "triangle": "EUR-USD-AUD",
          "baseline_r2": 0.7079,
          "new_r2": 0.9627791700366652,
          "improvement": 0.25487917003666527,
          "improvement_pct": 36.00496822102914,
          "kept": true,
          "num_features": 10
        },
        {
          "triangle": "EUR-USD-CAD",
          "baseline_r2": 0.7079,
          "new_r2": 0.9654955465222615,
          "improvement": 0.2575955465222616,
          "improvement_pct": 36.388691414361006,
          "kept": true,
          "num_features": 10
        },
        {
          "triangle": "EUR-USD-NZD",
          "baseline_r2": 0.7079,
          "new_r2": 0.9625669010318565,
          "improvement": 0.2546669010318565,
          "improvement_pct": 35.974982487901755,
          "kept": true,
          "num_features": 10
        },
        {
          "triangle": "EUR-GBP-JPY",
          "baseline_r2": 0.7079,
          "new_r2": 0.9607677036863431,
          "improvement": 0.25286770368634315,
          "improvement_pct": 35.720822670764676,
          "kept": true,
          "num_features": 10
        },
        {
          "triangle": "EUR-GBP-CHF",
          "baseline_r2": 0.7079,
          "new_r2": 0.9606816410353305,
          "improvement": 0.2527816410353305,
          "improvement_pct": 35.708665211941025,
          "kept": true,
          "num_features": 10
        },
        {
          "triangle": "EUR-GBP-AUD",
          "baseline_r2": 0.7079,
          "new_r2": 0.9603566625070408,
          "improvement": 0.2524566625070408,
          "improvement_pct": 35.66275780576929,
          "kept": true,
          "num_features": 10
        },
        {
          "triangle": "EUR-GBP-CAD",
          "baseline_r2": 0.7079,
          "new_r2": 0.9609075459958324,
          "improvement": 0.2530075459958324,
          "improvement_pct": 35.74057719958079,
          "kept": true,
          "num_features": 10
        }
      ]
    }
  ]
}