{
  "notes_standardization": {
    "version": "2.0",
    "mode": "APPEND - Never Replace",
    "effective_date": "2025-11-27T04:00:00.000000",
    "mandatory": true,
    "critical_change": "Notes must be APPENDED (prepended on top), not replaced",
    "format": {
      "header": "[STATUS_ICON] [STATUS_TEXT]: [ISO_TIMESTAMP]",
      "separator": "================================================",
      "separator_length": 48,
      "content": "Structured sections with clear headings",
      "order": "Newest updates on TOP, history preserved below"
    },
    "update_protocol": {
      "step1": "READ existing notes content",
      "step2": "CREATE new update block with timestamp",
      "step3": "PREPEND new block to top of existing",
      "step4": "PRESERVE all previous updates below",
      "step5": "SAVE complete history to AirTable"
    },
    "status_icons": {
      "completed": {
        "icon": "✅",
        "text": "COMPLETED",
        "color": "green",
        "usage": "Task successfully finished"
      },
      "in_progress": {
        "icon": "🔄",
        "text": "IN PROGRESS",
        "color": "blue",
        "usage": "Task actively being worked on"
      },
      "planned": {
        "icon": "📋",
        "text": "PLANNED",
        "color": "gray",
        "usage": "Task scheduled but not started"
      },
      "blocked": {
        "icon": "🚫",
        "text": "BLOCKED",
        "color": "red",
        "usage": "Task blocked by dependency or issue"
      },
      "cancelled": {
        "icon": "❌",
        "text": "CANCELLED",
        "color": "dark_red",
        "usage": "Task no longer needed or superseded"
      },
      "restated": {
        "icon": "🔀",
        "text": "RESTATED",
        "color": "orange",
        "usage": "Task reformulated with new scope"
      }
    },
    "timestamp_format": {
      "standard": "ISO 8601",
      "pattern": "YYYY-MM-DDTHH:MM:SS.mmmmmm",
      "example": "2025-11-27T00:29:11.102885",
      "python": "datetime.now().isoformat()"
    },
    "content_guidelines": [
      "Start with task name or context in CAPS",
      "Use bullet points (•, -, or *) for lists",
      "Include metrics and results where applicable",
      "Organize content in logical sections",
      "Keep within 48-character separator lines",
      "NEVER delete previous updates",
      "ALWAYS add new updates on top"
    ],
    "validation_requirements": [
      "Correct status icon must be used",
      "Status text must be in UPPERCASE",
      "Valid ISO timestamp required",
      "Exactly 48 equals signs in separators",
      "Content must be organized in sections",
      "Previous content must be preserved",
      "New timestamp must be newer than previous"
    ],
    "enforcement": {
      "new_tasks": "Must use append mode immediately",
      "existing_tasks": "Next update starts append chain",
      "automated_validation": true,
      "non_compliant_handling": "Replacement updates will be rejected",
      "history_deletion": "FORBIDDEN - immediate escalation"
    },
    "agent_responsibilities": {
      "chief_engineer": "Define and maintain standards",
      "builder_agent": "Append all updates, preserve history",
      "all_agents": "Never replace, always append on top"
    },
    "update_triggers": [
      "Task status change",
      "Milestone reached",
      "Issue encountered",
      "Progress update",
      "Completion",
      "Blocking event"
    ],
    "benefits_of_append_mode": [
      "Complete audit trail maintained",
      "Task evolution visible",
      "Decision history preserved",
      "Debugging easier with history",
      "Accountability through timestamps",
      "Knowledge transfer improved"
    ],
    "reference_files": [
      "/docs/AIRTABLE_NOTES_STANDARDIZATION_GUIDE_V2.md",
      "/scripts/append_airtable_note.py",
      "/scripts/standardize_airtable_notes.py",
      "/intelligence/airtable_standards.json"
    ]
  },
  "field_requirements": {
    "notes": {
      "required": true,
      "min_length": 50,
      "max_length": 50000,
      "must_follow_standard": true,
      "append_mode": true,
      "history_preservation": "mandatory"
    },
    "description": {
      "required": true,
      "min_length": 100,
      "max_length": 1000
    },
    "name": {
      "required": true,
      "max_length": 100
    },
    "task_id": {
      "required": true,
      "format": "MP03.P[0-9]{2}.S[0-9]{2}.T[0-9]{2}"
    },
    "status": {
      "required": true,
      "allowed_values": ["Todo", "In Progress", "Done", "Blocked", "Not Started", "Cancelled", "Restated"]
    },
    "priority": {
      "required": true,
      "allowed_values": ["Critical", "High", "Medium", "Low"]
    }
  },
  "update_frequency": {
    "in_progress_tasks": "Every significant milestone",
    "completed_tasks": "Final update with results",
    "blocked_tasks": "When blocked and when resolved",
    "planned_tasks": "When status changes",
    "all_tasks": "Append new update, never replace"
  },
  "compliance_metrics": {
    "total_tasks": 228,
    "standardized": 221,
    "append_mode_active": true,
    "compliance_rate": "100%",
    "last_audit": "2025-11-27T04:00:00.000000",
    "version_migration": "v1.0 (replace) → v2.0 (append)"
  },
  "critical_rules": {
    "always": [
      "Add new updates to TOP",
      "Keep ALL previous updates",
      "Use consistent formatting",
      "Include timestamp in every update",
      "Maintain chronological order (newest first)"
    ],
    "never": [
      "Delete previous updates",
      "Replace entire notes field",
      "Edit historical entries",
      "Merge updates together",
      "Skip timestamps"
    ]
  }
}